{"title":"Hello World","uid":"b9663f58f18133b35bfe243f3e916a80","slug":"hello-world","date":"2023-06-30T02:12:09.090Z","updated":"2023-06-30T14:07:32.535Z","comments":true,"path":"api/articles/hello-world.json","keywords":null,"cover":null,"content":"<p>Welcome to <a href=\"https://hexo.io/\">Hexo</a>! This is your very first post. Check <a href=\"https://hexo.io/docs/\">documentation</a> for more info. If you get any problems when using Hexo, you can find the answer in <a href=\"https://hexo.io/docs/troubleshooting.html\">troubleshooting</a> or you can ask me on <a href=\"https://github.com/hexojs/hexo/issues\">GitHub</a>.</p>\n<h2 id=\"Quick-Start\"><a href=\"#Quick-Start\" class=\"headerlink\" title=\"Quick Start\"></a>Quick Start</h2><h3 id=\"Create-a-new-post\"><a href=\"#Create-a-new-post\" class=\"headerlink\" title=\"Create a new post\"></a>Create a new post</h3><div class=\"language-bash\"><button title=\"Copy code\" class=\"copy\"></button><span class=\"lang\">bash</span><pre class=\"shiki \" style=\"background-color: #1a1a1a\" tabindex=\"0\"><code><span class=\"line\"><span style=\"color: #88C0D0\">$</span><span style=\"color: #D8DEE9FF\"> </span><span style=\"color: #A3BE8C\">hexo</span><span style=\"color: #D8DEE9FF\"> </span><span style=\"color: #A3BE8C\">new</span><span style=\"color: #D8DEE9FF\"> </span><span style=\"color: #ECEFF4\">&quot;</span><span style=\"color: #A3BE8C\">My New Post</span><span style=\"color: #ECEFF4\">&quot;</span></span></code></pre></div>\n\n<p>More info: <a href=\"https://hexo.io/docs/writing.html\">Writing</a></p>\n<h3 id=\"Run-server\"><a href=\"#Run-server\" class=\"headerlink\" title=\"Run server\"></a>Run server</h3><div class=\"language-bash\"><button title=\"Copy code\" class=\"copy\"></button><span class=\"lang\">bash</span><pre class=\"shiki \" style=\"background-color: #1a1a1a\" tabindex=\"0\"><code><span class=\"line\"><span style=\"color: #88C0D0\">$</span><span style=\"color: #D8DEE9FF\"> </span><span style=\"color: #A3BE8C\">hexo</span><span style=\"color: #D8DEE9FF\"> </span><span style=\"color: #A3BE8C\">server</span></span></code></pre></div>\n\n<p>More info: <a href=\"https://hexo.io/docs/server.html\">Server</a></p>\n<h3 id=\"Generate-static-files\"><a href=\"#Generate-static-files\" class=\"headerlink\" title=\"Generate static files\"></a>Generate static files</h3><div class=\"language-bash\"><button title=\"Copy code\" class=\"copy\"></button><span class=\"lang\">bash</span><pre class=\"shiki \" style=\"background-color: #1a1a1a\" tabindex=\"0\"><code><span class=\"line\"><span style=\"color: #88C0D0\">$</span><span style=\"color: #D8DEE9FF\"> </span><span style=\"color: #A3BE8C\">hexo</span><span style=\"color: #D8DEE9FF\"> </span><span style=\"color: #A3BE8C\">generate</span></span></code></pre></div>\n\n<p>More info: <a href=\"https://hexo.io/docs/generating.html\">Generating</a></p>\n<h3 id=\"Deploy-to-remote-sites\"><a href=\"#Deploy-to-remote-sites\" class=\"headerlink\" title=\"Deploy to remote sites\"></a>Deploy to remote sites</h3><div class=\"language-bash\"><button title=\"Copy code\" class=\"copy\"></button><span class=\"lang\">bash</span><pre class=\"shiki \" style=\"background-color: #1a1a1a\" tabindex=\"0\"><code><span class=\"line\"><span style=\"color: #88C0D0\">$</span><span style=\"color: #D8DEE9FF\"> </span><span style=\"color: #A3BE8C\">hexo</span><span style=\"color: #D8DEE9FF\"> </span><span style=\"color: #A3BE8C\">deploy</span></span></code></pre></div>\n\n<p>More info: <a href=\"https://hexo.io/docs/one-command-deployment.html\">Deployment</a></p>\n","feature":false,"text":"Welcome to Hexo! This is your very first post. Check documentation for more info...","permalink":"/post/hello-world","photos":[],"count_time":{"symbolsCount":456,"symbolsTime":"1 mins."},"categories":[],"tags":[],"toc":"<ol class=\"toc\"><li class=\"toc-item toc-level-2\"><a class=\"toc-link\" href=\"#Quick-Start\"><span class=\"toc-text\">Quick Start</span></a><ol class=\"toc-child\"><li class=\"toc-item toc-level-3\"><a class=\"toc-link\" href=\"#Create-a-new-post\"><span class=\"toc-text\">Create a new post</span></a></li><li class=\"toc-item toc-level-3\"><a class=\"toc-link\" href=\"#Run-server\"><span class=\"toc-text\">Run server</span></a></li><li class=\"toc-item toc-level-3\"><a class=\"toc-link\" href=\"#Generate-static-files\"><span class=\"toc-text\">Generate static files</span></a></li><li class=\"toc-item toc-level-3\"><a class=\"toc-link\" href=\"#Deploy-to-remote-sites\"><span class=\"toc-text\">Deploy to remote sites</span></a></li></ol></li></ol>","author":{"name":"Mr.jiu","slug":"blog-author","avatar":"https://img1.imgtp.com/2023/08/07/t5mbWPLz.png","link":"/","description":"不从善恶意，只遵本心行","socials":{"github":"","twitter":"","stackoverflow":"","wechat":"","qq":"","weibo":"","zhihu":"","csdn":"","juejin":"","customs":{}}},"mapped":true,"hidden":false,"prev_post":{"title":"蔡徐坤","uid":"bfc404b33da84ce2df9a7a3ee0f3842d","slug":"蔡徐坤","date":"2023-06-30T06:52:39.000Z","updated":"2023-06-30T14:07:14.588Z","comments":true,"path":"api/articles/蔡徐坤.json","keywords":null,"cover":"https://i.imgtg.com/2023/06/30/OkG5aU.jpg","text":"个人简介蔡徐坤（KUN，1998年8月2日-），出生于浙江省温州市，中国内地男歌手、原创音乐制作人、MV导演、演员。 2012年4月，因参加综艺节目《向上吧！少...","permalink":"/post/蔡徐坤","photos":[],"count_time":{"symbolsCount":713,"symbolsTime":"1 mins."},"categories":[{"name":"其他","slug":"其他","count":3,"path":"api/categories/其他.json"}],"tags":[{"name":"其他","slug":"其他","count":3,"path":"api/tags/其他.json"}],"author":{"name":"Mr.jiu","slug":"blog-author","avatar":"https://img1.imgtp.com/2023/08/07/t5mbWPLz.png","link":"/","description":"不从善恶意，只遵本心行","socials":{"github":"","twitter":"","stackoverflow":"","wechat":"","qq":"","weibo":"","zhihu":"","csdn":"","juejin":"","customs":{}}},"feature":false},"next_post":{}}